[{"id":"0.017024328384290133","title":"Natraj pencil","imageUrl":"https://tse3.mm.bing.net/th?id=OIP.JhomoKsPJhJzoLYIoawnqwHaGq&pid=Api&P=0&h=180","description":"branded pencil","price":"20"},{"title":"fivth book","imageUrl":"https://tse1.mm.bing.net/th?id=OIP.rGiuWvU04EDsWLBejxraWwAAAA&pid=Api&P=0&h=180","description":"religious book","price":"200","id":"0.3344955241973919"},{"id":"0.7893938583396114","title":"A Simple Book","imageUrl":"https://www.publicdomainpictures.net/pictures/10000/velka/1-1210009435EGmE.jpg","description":"This is an awesome book!","price":"19"},{"id":"0.0009352486620171074","title":"A Simple Book","imageUrl":"https://www.publicdomainpictures.net/pictures/10000/velka/1-1210009435EGmE.jpg","description":"This is an awesome book!","price":"19"}]